mux_4in_1out.v
`timescale 1ns/10ps
//Modulo de descripcion del 
//circuito multiplexor 4 entradas a 1 salida
module mux_4in_1out(
    input  [3:0] I,
    input [1:0] sel,
    output Q);
        wire a,b,c,d,sel0,sel1;
        not (sel1,sel[1]);
        not (sel0,sel[0]);
        and (a,I[0],sel1,sel0);      // selection bits 00
        and (b,I[1],sel1,sel[0]);    // selection bits 01
        and (c,I[2],sel[1],sel0);    // selection bits 10
        and (d,I[3],sel[1],sel[0]);  // selection bits 11
        or (Q,a,b,c,d);
endmodule

test_mux_4in_1out.v
`timescale 1ns/10ps
//Modulo de estimulo para el
//circuito multiplexor 4 entradas a 1 salida
module test_mux_4in_1out ();
    reg in0, in1, in2, in3;
    reg [1:0] select;
    wire out;
    mux_4in_1out mux4in1out({in3, in2, in1, in0},select,out);
    always #0.1     in0=~in0;
    always #0.5     in1=~in1;
    always #1       in2=~in2;
    always #5       in3=~in3;

    initial begin
        $dumpfile("out_mux.vcd");
        $dumpvars(0,test_mux_4in_1out);
        in0=0;in1=0;in2=0;in3=0;
        select=2'b00;
        #20
        select=2'b01;
        #20
        select=2'b10;
        #20
        select=2'b11;
        #20 
        $finish;
    end
endmodule

out_mux.vcd
$date
	Fri Feb  5 16:50:45 2021
$end
$version
	Icarus Verilog
$end
$timescale
	10ps
$end
$scope module test_mux_4in_1out $end
$var wire 1 ! out $end
$var reg 1 " in0 $end
$var reg 1 # in1 $end
$var reg 1 $ in2 $end
$var reg 1 % in3 $end
$var reg 2 & select [1:0] $end
$scope module mux4in1out $end
$var wire 4 ' I [3:0] $end
$var wire 1 ! Q $end
$var wire 1 ( a $end
$var wire 1 ) b $end
$var wire 1 * c $end
$var wire 1 + d $end
$var wire 2 , sel [1:0] $end
$var wire 1 - sel0 $end
$var wire 1 . sel1 $end
$upscope $end
$upscope $end
$enddefinitions $end
#0
$dumpvars
1.
1-
b0 ,
0+
0*
0)
0(
b0 '
b0 &
0%
0$
0#
0"
0!
$end
#10
1!
1(
b1 '
1"
#20
0!
0(
b0 '
0"
#30
1!
1(
b1 '
1"
#40
0!
0(
b0 '
0"
#50
1!
1(
1"
b11 '
1#
#60
0!
0(
b10 '
0"
#70
1!
1(
b11 '
1"
#80
0!
0(
b10 '
0"
#90
1!
1(
b11 '
1"
#100
0!
0(
0"
0#
b100 '
1$
#110
1!
1(
b101 '
1"
#120
0!
0(
b100 '
0"
#130
1!
1(
b101 '
1"
#140
0!
0(
b100 '
0"
#150
1!
1(
1"
b111 '
1#
#160
0!
0(
b110 '
0"
#170
1!
1(
b111 '
1"
#180
0!
0(
b110 '
0"
#190
1!
1(
b111 '
1"
#200
0!
0(
0"
0#
b0 '
0$
#210
1!
1(
b1 '
1"
#220
0!
0(
b0 '
0"
#230
1!
1(
b1 '
1"
#240
0!
0(
b0 '
0"
#250
1!
1(
1"
b11 '
1#
#260
0!
0(
b10 '
0"
#270
1!
1(
b11 '
1"
#280
0!
0(
b10 '
0"
#290
1!
1(
b11 '
1"
#300
0!
0(
0"
0#
b100 '
1$
#310
1!
1(
b101 '
1"
#320
0!
0(
b100 '
0"
#330
1!
1(
b101 '
1"
#340
0!
0(
b100 '
0"
#350
1!
1(
1"
b111 '
1#
#360
0!
0(
b110 '
0"
#370
1!
1(
b111 '
1"
#380
0!
0(
b110 '
0"
#390
1!
1(
b111 '
1"
#400
0!
0(
0"
0#
b0 '
0$
#410
1!
1(
b1 '
1"
#420
0!
0(
b0 '
0"
#430
1!
1(
b1 '
1"
#440
0!
0(
b0 '
0"
#450
1!
1(
1"
b11 '
1#
#460
0!
0(
b10 '
0"
#470
1!
1(
b11 '
1"
#480
0!
0(
b10 '
0"
#490
1!
1(
b11 '
1"
#500
0!
0(
0"
0#
1$
b1100 '
1%
#510
1!
1(
b1101 '
1"
#520
0!
0(
b1100 '
0"
#530
1!
1(
b1101 '
1"
#540
0!
0(
b1100 '
0"
#550
1!
1(
1"
b1111 '
1#
#560
0!
0(
b1110 '
0"
#570
1!
1(
b1111 '
1"
#580
0!
0(
b1110 '
0"
#590
1!
1(
b1111 '
1"
#600
0!
0(
0"
0#
b1000 '
0$
#610
1!
1(
b1001 '
1"
#620
0!
0(
b1000 '
0"
#630
1!
1(
b1001 '
1"
#640
0!
0(
b1000 '
0"
#650
1!
1(
1"
b1011 '
1#
#660
0!
0(
b1010 '
0"
#670
1!
1(
b1011 '
1"
#680
0!
0(
b1010 '
0"
#690
1!
1(
b1011 '
1"
#700
0!
0(
0"
0#
b1100 '
1$
#710
1!
1(
b1101 '
1"
#720
0!
0(
b1100 '
0"
#730
1!
1(
b1101 '
1"
#740
0!
0(
b1100 '
0"
#750
1!
1(
1"
b1111 '
1#
#760
0!
0(
b1110 '
0"
#770
1!
1(
b1111 '
1"
#780
0!
0(
b1110 '
0"
#790
1!
1(
b1111 '
1"
#800
0!
0(
0"
0#
b1000 '
0$
#810
1!
1(
b1001 '
1"
#820
0!
0(
b1000 '
0"
#830
1!
1(
b1001 '
1"
#840
0!
0(
b1000 '
0"
#850
1!
1(
1"
b1011 '
1#
#860
0!
0(
b1010 '
0"
#870
1!
1(
b1011 '
1"
#880
0!
0(
b1010 '
0"
#890
1!
1(
b1011 '
1"
#900
0!
0(
0"
0#
b1100 '
1$
#910
1!
1(
b1101 '
1"
#920
0!
0(
b1100 '
0"
#930
1!
1(
b1101 '
1"
#940
0!
0(
b1100 '
0"
#950
1!
1(
1"
b1111 '
1#
#960
0!
0(
b1110 '
0"
#970
1!
1(
b1111 '
1"
#980
0!
0(
b1110 '
0"
#990
1!
1(
b1111 '
1"
#1000
0!
0(
0"
0#
0$
b0 '
0%
#1010
1!
1(
b1 '
1"
#1020
0!
0(
b0 '
0"
#1030
1!
1(
b1 '
1"
#1040
0!
0(
b0 '
0"
#1050
1!
1(
1"
b11 '
1#
#1060
0!
0(
b10 '
0"
#1070
1!
1(
b11 '
1"
#1080
0!
0(
b10 '
0"
#1090
1!
1(
b11 '
1"
#1100
0!
0(
0"
0#
b100 '
1$
#1110
1!
1(
b101 '
1"
#1120
0!
0(
b100 '
0"
#1130
1!
1(
b101 '
1"
#1140
0!
0(
b100 '
0"
#1150
1!
1(
1"
b111 '
1#
#1160
0!
0(
b110 '
0"
#1170
1!
1(
b111 '
1"
#1180
0!
0(
b110 '
0"
#1190
1!
1(
b111 '
1"
#1200
0!
0(
0"
0#
b0 '
0$
#1210
1!
1(
b1 '
1"
#1220
0!
0(
b0 '
0"
#1230
1!
1(
b1 '
1"
#1240
0!
0(
b0 '
0"
#1250
1!
1(
1"
b11 '
1#
#1260
0!
0(
b10 '
0"
#1270
1!
1(
b11 '
1"
#1280
0!
0(
b10 '
0"
#1290
1!
1(
b11 '
1"
#1300
0!
0(
0"
0#
b100 '
1$
#1310
1!
1(
b101 '
1"
#1320
0!
0(
b100 '
0"
#1330
1!
1(
b101 '
1"
#1340
0!
0(
b100 '
0"
#1350
1!
1(
1"
b111 '
1#
#1360
0!
0(
b110 '
0"
#1370
1!
1(
b111 '
1"
#1380
0!
0(
b110 '
0"
#1390
1!
1(
b111 '
1"
#1400
0!
0(
0"
0#
b0 '
0$
#1410
1!
1(
b1 '
1"
#1420
0!
0(
b0 '
0"
#1430
1!
1(
b1 '
1"
#1440
0!
0(
b0 '
0"
#1450
1!
1(
1"
b11 '
1#
#1460
0!
0(
b10 '
0"
#1470
1!
1(
b11 '
1"
#1480
0!
0(
b10 '
0"
#1490
1!
1(
b11 '
1"
#1500
0!
0(
0"
0#
1$
b1100 '
1%
#1510
1!
1(
b1101 '
1"
#1520
0!
0(
b1100 '
0"
#1530
1!
1(
b1101 '
1"
#1540
0!
0(
b1100 '
0"
#1550
1!
1(
1"
b1111 '
1#
#1560
0!
0(
b1110 '
0"
#1570
1!
1(
b1111 '
1"
#1580
0!
0(
b1110 '
0"
#1590
1!
1(
b1111 '
1"
#1600
0!
0(
0"
0#
b1000 '
0$
#1610
1!
1(
b1001 '
1"
#1620
0!
0(
b1000 '
0"
#1630
1!
1(
b1001 '
1"
#1640
0!
0(
b1000 '
0"
#1650
1!
1(
1"
b1011 '
1#
#1660
0!
0(
b1010 '
0"
#1670
1!
1(
b1011 '
1"
#1680
0!
0(
b1010 '
0"
#1690
1!
1(
b1011 '
1"
#1700
0!
0(
0"
0#
b1100 '
1$
#1710
1!
1(
b1101 '
1"
#1720
0!
0(
b1100 '
0"
#1730
1!
1(
b1101 '
1"
#1740
0!
0(
b1100 '
0"
#1750
1!
1(
1"
b1111 '
1#
#1760
0!
0(
b1110 '
0"
#1770
1!
1(
b1111 '
1"
#1780
0!
0(
b1110 '
0"
#1790
1!
1(
b1111 '
1"
#1800
0!
0(
0"
0#
b1000 '
0$
#1810
1!
1(
b1001 '
1"
#1820
0!
0(
b1000 '
0"
#1830
1!
1(
b1001 '
1"
#1840
0!
0(
b1000 '
0"
#1850
1!
1(
1"
b1011 '
1#
#1860
0!
0(
b1010 '
0"
#1870
1!
1(
b1011 '
1"
#1880
0!
0(
b1010 '
0"
#1890
1!
1(
b1011 '
1"
#1900
0!
0(
0"
0#
b1100 '
1$
#1910
1!
1(
b1101 '
1"
#1920
0!
0(
b1100 '
0"
#1930
1!
1(
b1101 '
1"
#1940
0!
0(
b1100 '
0"
#1950
1!
1(
1"
b1111 '
1#
#1960
0!
0(
b1110 '
0"
#1970
1!
1(
b1111 '
1"
#1980
0!
0(
b1110 '
0"
#1990
1!
1(
b1111 '
1"
#2000
0!
0(
0-
0"
0#
0$
b0 '
0%
b1 &
b1 ,
#2010
b1 '
1"
#2020
b0 '
0"
#2030
b1 '
1"
#2040
b0 '
0"
#2050
1!
1)
1"
b11 '
1#
#2060
b10 '
0"
#2070
b11 '
1"
#2080
b10 '
0"
#2090
b11 '
1"
#2100
0!
0)
0"
0#
b100 '
1$
#2110
b101 '
1"
#2120
b100 '
0"
#2130
b101 '
1"
#2140
b100 '
0"
#2150
1!
1)
1"
b111 '
1#
#2160
b110 '
0"
#2170
b111 '
1"
#2180
b110 '
0"
#2190
b111 '
1"
#2200
0!
0)
0"
0#
b0 '
0$
#2210
b1 '
1"
#2220
b0 '
0"
#2230
b1 '
1"
#2240
b0 '
0"
#2250
1!
1)
1"
b11 '
1#
#2260
b10 '
0"
#2270
b11 '
1"
#2280
b10 '
0"
#2290
b11 '
1"
#2300
0!
0)
0"
0#
b100 '
1$
#2310
b101 '
1"
#2320
b100 '
0"
#2330
b101 '
1"
#2340
b100 '
0"
#2350
1!
1)
1"
b111 '
1#
#2360
b110 '
0"
#2370
b111 '
1"
#2380
b110 '
0"
#2390
b111 '
1"
#2400
0!
0)
0"
0#
b0 '
0$
#2410
b1 '
1"
#2420
b0 '
0"
#2430
b1 '
1"
#2440
b0 '
0"
#2450
1!
1)
1"
b11 '
1#
#2460
b10 '
0"
#2470
b11 '
1"
#2480
b10 '
0"
#2490
b11 '
1"
#2500
0!
0)
0"
0#
1$
b1100 '
1%
#2510
b1101 '
1"
#2520
b1100 '
0"
#2530
b1101 '
1"
#2540
b1100 '
0"
#2550
1!
1)
1"
b1111 '
1#
#2560
b1110 '
0"
#2570
b1111 '
1"
#2580
b1110 '
0"
#2590
b1111 '
1"
#2600
0!
0)
0"
0#
b1000 '
0$
#2610
b1001 '
1"
#2620
b1000 '
0"
#2630
b1001 '
1"
#2640
b1000 '
0"
#2650
1!
1)
1"
b1011 '
1#
#2660
b1010 '
0"
#2670
b1011 '
1"
#2680
b1010 '
0"
#2690
b1011 '
1"
#2700
0!
0)
0"
0#
b1100 '
1$
#2710
b1101 '
1"
#2720
b1100 '
0"
#2730
b1101 '
1"
#2740
b1100 '
0"
#2750
1!
1)
1"
b1111 '
1#
#2760
b1110 '
0"
#2770
b1111 '
1"
#2780
b1110 '
0"
#2790
b1111 '
1"
#2800
0!
0)
0"
0#
b1000 '
0$
#2810
b1001 '
1"
#2820
b1000 '
0"
#2830
b1001 '
1"
#2840
b1000 '
0"
#2850
1!
1)
1"
b1011 '
1#
#2860
b1010 '
0"
#2870
b1011 '
1"
#2880
b1010 '
0"
#2890
b1011 '
1"
#2900
0!
0)
0"
0#
b1100 '
1$
#2910
b1101 '
1"
#2920
b1100 '
0"
#2930
b1101 '
1"
#2940
b1100 '
0"
#2950
1!
1)
1"
b1111 '
1#
#2960
b1110 '
0"
#2970
b1111 '
1"
#2980
b1110 '
0"
#2990
b1111 '
1"
#3000
0!
0)
0"
0#
0$
b0 '
0%
#3010
b1 '
1"
#3020
b0 '
0"
#3030
b1 '
1"
#3040
b0 '
0"
#3050
1!
1)
1"
b11 '
1#
#3060
b10 '
0"
#3070
b11 '
1"
#3080
b10 '
0"
#3090
b11 '
1"
#3100
0!
0)
0"
0#
b100 '
1$
#3110
b101 '
1"
#3120
b100 '
0"
#3130
b101 '
1"
#3140
b100 '
0"
#3150
1!
1)
1"
b111 '
1#
#3160
b110 '
0"
#3170
b111 '
1"
#3180
b110 '
0"
#3190
b111 '
1"
#3200
0!
0)
0"
0#
b0 '
0$
#3210
b1 '
1"
#3220
b0 '
0"
#3230
b1 '
1"
#3240
b0 '
0"
#3250
1!
1)
1"
b11 '
1#
#3260
b10 '
0"
#3270
b11 '
1"
#3280
b10 '
0"
#3290
b11 '
1"
#3300
0!
0)
0"
0#
b100 '
1$
#3310
b101 '
1"
#3320
b100 '
0"
#3330
b101 '
1"
#3340
b100 '
0"
#3350
1!
1)
1"
b111 '
1#
#3360
b110 '
0"
#3370
b111 '
1"
#3380
b110 '
0"
#3390
b111 '
1"
#3400
0!
0)
0"
0#
b0 '
0$
#3410
b1 '
1"
#3420
b0 '
0"
#3430
b1 '
1"
#3440
b0 '
0"
#3450
1!
1)
1"
b11 '
1#
#3460
b10 '
0"
#3470
b11 '
1"
#3480
b10 '
0"
#3490
b11 '
1"
#3500
0!
0)
0"
0#
1$
b1100 '
1%
#3510
b1101 '
1"
#3520
b1100 '
0"
#3530
b1101 '
1"
#3540
b1100 '
0"
#3550
1!
1)
1"
b1111 '
1#
#3560
b1110 '
0"
#3570
b1111 '
1"
#3580
b1110 '
0"
#3590
b1111 '
1"
#3600
0!
0)
0"
0#
b1000 '
0$
#3610
b1001 '
1"
#3620
b1000 '
0"
#3630
b1001 '
1"
#3640
b1000 '
0"
#3650
1!
1)
1"
b1011 '
1#
#3660
b1010 '
0"
#3670
b1011 '
1"
#3680
b1010 '
0"
#3690
b1011 '
1"
#3700
0!
0)
0"
0#
b1100 '
1$
#3710
b1101 '
1"
#3720
b1100 '
0"
#3730
b1101 '
1"
#3740
b1100 '
0"
#3750
1!
1)
1"
b1111 '
1#
#3760
b1110 '
0"
#3770
b1111 '
1"
#3780
b1110 '
0"
#3790
b1111 '
1"
#3800
0!
0)
0"
0#
b1000 '
0$
#3810
b1001 '
1"
#3820
b1000 '
0"
#3830
b1001 '
1"
#3840
b1000 '
0"
#3850
1!
1)
1"
b1011 '
1#
#3860
b1010 '
0"
#3870
b1011 '
1"
#3880
b1010 '
0"
#3890
b1011 '
1"
#3900
0!
0)
0"
0#
b1100 '
1$
#3910
b1101 '
1"
#3920
b1100 '
0"
#3930
b1101 '
1"
#3940
b1100 '
0"
#3950
1!
1)
1"
b1111 '
1#
#3960
b1110 '
0"
#3970
b1111 '
1"
#3980
b1110 '
0"
#3990
b1111 '
1"
#4000
0!
0.
1-
0)
0"
0#
0$
b0 '
0%
b10 &
b10 ,
#4010
b1 '
1"
#4020
b0 '
0"
#4030
b1 '
1"
#4040
b0 '
0"
#4050
1"
b11 '
1#
#4060
b10 '
0"
#4070
b11 '
1"
#4080
b10 '
0"
#4090
b11 '
1"
#4100
1!
1*
0"
0#
b100 '
1$
#4110
b101 '
1"
#4120
b100 '
0"
#4130
b101 '
1"
#4140
b100 '
0"
#4150
1"
b111 '
1#
#4160
b110 '
0"
#4170
b111 '
1"
#4180
b110 '
0"
#4190
b111 '
1"
#4200
0!
0*
0"
0#
b0 '
0$
#4210
b1 '
1"
#4220
b0 '
0"
#4230
b1 '
1"
#4240
b0 '
0"
#4250
1"
b11 '
1#
#4260
b10 '
0"
#4270
b11 '
1"
#4280
b10 '
0"
#4290
b11 '
1"
#4300
1!
1*
0"
0#
b100 '
1$
#4310
b101 '
1"
#4320
b100 '
0"
#4330
b101 '
1"
#4340
b100 '
0"
#4350
1"
b111 '
1#
#4360
b110 '
0"
#4370
b111 '
1"
#4380
b110 '
0"
#4390
b111 '
1"
#4400
0!
0*
0"
0#
b0 '
0$
#4410
b1 '
1"
#4420
b0 '
0"
#4430
b1 '
1"
#4440
b0 '
0"
#4450
1"
b11 '
1#
#4460
b10 '
0"
#4470
b11 '
1"
#4480
b10 '
0"
#4490
b11 '
1"
#4500
1!
1*
0"
0#
1$
b1100 '
1%
#4510
b1101 '
1"
#4520
b1100 '
0"
#4530
b1101 '
1"
#4540
b1100 '
0"
#4550
1"
b1111 '
1#
#4560
b1110 '
0"
#4570
b1111 '
1"
#4580
b1110 '
0"
#4590
b1111 '
1"
#4600
0!
0*
0"
0#
b1000 '
0$
#4610
b1001 '
1"
#4620
b1000 '
0"
#4630
b1001 '
1"
#4640
b1000 '
0"
#4650
1"
b1011 '
1#
#4660
b1010 '
0"
#4670
b1011 '
1"
#4680
b1010 '
0"
#4690
b1011 '
1"
#4700
1!
1*
0"
0#
b1100 '
1$
#4710
b1101 '
1"
#4720
b1100 '
0"
#4730
b1101 '
1"
#4740
b1100 '
0"
#4750
1"
b1111 '
1#
#4760
b1110 '
0"
#4770
b1111 '
1"
#4780
b1110 '
0"
#4790
b1111 '
1"
#4800
0!
0*
0"
0#
b1000 '
0$
#4810
b1001 '
1"
#4820
b1000 '
0"
#4830
b1001 '
1"
#4840
b1000 '
0"
#4850
1"
b1011 '
1#
#4860
b1010 '
0"
#4870
b1011 '
1"
#4880
b1010 '
0"
#4890
b1011 '
1"
#4900
1!
1*
0"
0#
b1100 '
1$
#4910
b1101 '
1"
#4920
b1100 '
0"
#4930
b1101 '
1"
#4940
b1100 '
0"
#4950
1"
b1111 '
1#
#4960
b1110 '
0"
#4970
b1111 '
1"
#4980
b1110 '
0"
#4990
b1111 '
1"
#5000
0!
0*
0"
0#
0$
b0 '
0%
#5010
b1 '
1"
#5020
b0 '
0"
#5030
b1 '
1"
#5040
b0 '
0"
#5050
1"
b11 '
1#
#5060
b10 '
0"
#5070
b11 '
1"
#5080
b10 '
0"
#5090
b11 '
1"
#5100
1!
1*
0"
0#
b100 '
1$
#5110
b101 '
1"
#5120
b100 '
0"
#5130
b101 '
1"
#5140
b100 '
0"
#5150
1"
b111 '
1#
#5160
b110 '
0"
#5170
b111 '
1"
#5180
b110 '
0"
#5190
b111 '
1"
#5200
0!
0*
0"
0#
b0 '
0$
#5210
b1 '
1"
#5220
b0 '
0"
#5230
b1 '
1"
#5240
b0 '
0"
#5250
1"
b11 '
1#
#5260
b10 '
0"
#5270
b11 '
1"
#5280
b10 '
0"
#5290
b11 '
1"
#5300
1!
1*
0"
0#
b100 '
1$
#5310
b101 '
1"
#5320
b100 '
0"
#5330
b101 '
1"
#5340
b100 '
0"
#5350
1"
b111 '
1#
#5360
b110 '
0"
#5370
b111 '
1"
#5380
b110 '
0"
#5390
b111 '
1"
#5400
0!
0*
0"
0#
b0 '
0$
#5410
b1 '
1"
#5420
b0 '
0"
#5430
b1 '
1"
#5440
b0 '
0"
#5450
1"
b11 '
1#
#5460
b10 '
0"
#5470
b11 '
1"
#5480
b10 '
0"
#5490
b11 '
1"
#5500
1!
1*
0"
0#
1$
b1100 '
1%
#5510
b1101 '
1"
#5520
b1100 '
0"
#5530
b1101 '
1"
#5540
b1100 '
0"
#5550
1"
b1111 '
1#
#5560
b1110 '
0"
#5570
b1111 '
1"
#5580
b1110 '
0"
#5590
b1111 '
1"
#5600
0!
0*
0"
0#
b1000 '
0$
#5610
b1001 '
1"
#5620
b1000 '
0"
#5630
b1001 '
1"
#5640
b1000 '
0"
#5650
1"
b1011 '
1#
#5660
b1010 '
0"
#5670
b1011 '
1"
#5680
b1010 '
0"
#5690
b1011 '
1"
#5700
1!
1*
0"
0#
b1100 '
1$
#5710
b1101 '
1"
#5720
b1100 '
0"
#5730
b1101 '
1"
#5740
b1100 '
0"
#5750
1"
b1111 '
1#
#5760
b1110 '
0"
#5770
b1111 '
1"
#5780
b1110 '
0"
#5790
b1111 '
1"
#5800
0!
0*
0"
0#
b1000 '
0$
#5810
b1001 '
1"
#5820
b1000 '
0"
#5830
b1001 '
1"
#5840
b1000 '
0"
#5850
1"
b1011 '
1#
#5860
b1010 '
0"
#5870
b1011 '
1"
#5880
b1010 '
0"
#5890
b1011 '
1"
#5900
1!
1*
0"
0#
b1100 '
1$
#5910
b1101 '
1"
#5920
b1100 '
0"
#5930
b1101 '
1"
#5940
b1100 '
0"
#5950
1"
b1111 '
1#
#5960
b1110 '
0"
#5970
b1111 '
1"
#5980
b1110 '
0"
#5990
b1111 '
1"
#6000
0!
0*
0-
0"
0#
0$
b0 '
0%
b11 &
b11 ,
#6010
b1 '
1"
#6020
b0 '
0"
#6030
b1 '
1"
#6040
b0 '
0"
#6050
1"
b11 '
1#
#6060
b10 '
0"
#6070
b11 '
1"
#6080
b10 '
0"
#6090
b11 '
1"
#6100
0"
0#
b100 '
1$
#6110
b101 '
1"
#6120
b100 '
0"
#6130
b101 '
1"
#6140
b100 '
0"
#6150
1"
b111 '
1#
#6160
b110 '
0"
#6170
b111 '
1"
#6180
b110 '
0"
#6190
b111 '
1"
#6200
0"
0#
b0 '
0$
#6210
b1 '
1"
#6220
b0 '
0"
#6230
b1 '
1"
#6240
b0 '
0"
#6250
1"
b11 '
1#
#6260
b10 '
0"
#6270
b11 '
1"
#6280
b10 '
0"
#6290
b11 '
1"
#6300
0"
0#
b100 '
1$
#6310
b101 '
1"
#6320
b100 '
0"
#6330
b101 '
1"
#6340
b100 '
0"
#6350
1"
b111 '
1#
#6360
b110 '
0"
#6370
b111 '
1"
#6380
b110 '
0"
#6390
b111 '
1"
#6400
0"
0#
b0 '
0$
#6410
b1 '
1"
#6420
b0 '
0"
#6430
b1 '
1"
#6440
b0 '
0"
#6450
1"
b11 '
1#
#6460
b10 '
0"
#6470
b11 '
1"
#6480
b10 '
0"
#6490
b11 '
1"
#6500
1!
1+
0"
0#
1$
b1100 '
1%
#6510
b1101 '
1"
#6520
b1100 '
0"
#6530
b1101 '
1"
#6540
b1100 '
0"
#6550
1"
b1111 '
1#
#6560
b1110 '
0"
#6570
b1111 '
1"
#6580
b1110 '
0"
#6590
b1111 '
1"
#6600
0"
0#
b1000 '
0$
#6610
b1001 '
1"
#6620
b1000 '
0"
#6630
b1001 '
1"
#6640
b1000 '
0"
#6650
1"
b1011 '
1#
#6660
b1010 '
0"
#6670
b1011 '
1"
#6680
b1010 '
0"
#6690
b1011 '
1"
#6700
0"
0#
b1100 '
1$
#6710
b1101 '
1"
#6720
b1100 '
0"
#6730
b1101 '
1"
#6740
b1100 '
0"
#6750
1"
b1111 '
1#
#6760
b1110 '
0"
#6770
b1111 '
1"
#6780
b1110 '
0"
#6790
b1111 '
1"
#6800
0"
0#
b1000 '
0$
#6810
b1001 '
1"
#6820
b1000 '
0"
#6830
b1001 '
1"
#6840
b1000 '
0"
#6850
1"
b1011 '
1#
#6860
b1010 '
0"
#6870
b1011 '
1"
#6880
b1010 '
0"
#6890
b1011 '
1"
#6900
0"
0#
b1100 '
1$
#6910
b1101 '
1"
#6920
b1100 '
0"
#6930
b1101 '
1"
#6940
b1100 '
0"
#6950
1"
b1111 '
1#
#6960
b1110 '
0"
#6970
b1111 '
1"
#6980
b1110 '
0"
#6990
b1111 '
1"
#7000
0!
0+
0"
0#
0$
b0 '
0%
#7010
b1 '
1"
#7020
b0 '
0"
#7030
b1 '
1"
#7040
b0 '
0"
#7050
1"
b11 '
1#
#7060
b10 '
0"
#7070
b11 '
1"
#7080
b10 '
0"
#7090
b11 '
1"
#7100
0"
0#
b100 '
1$
#7110
b101 '
1"
#7120
b100 '
0"
#7130
b101 '
1"
#7140
b100 '
0"
#7150
1"
b111 '
1#
#7160
b110 '
0"
#7170
b111 '
1"
#7180
b110 '
0"
#7190
b111 '
1"
#7200
0"
0#
b0 '
0$
#7210
b1 '
1"
#7220
b0 '
0"
#7230
b1 '
1"
#7240
b0 '
0"
#7250
1"
b11 '
1#
#7260
b10 '
0"
#7270
b11 '
1"
#7280
b10 '
0"
#7290
b11 '
1"
#7300
0"
0#
b100 '
1$
#7310
b101 '
1"
#7320
b100 '
0"
#7330
b101 '
1"
#7340
b100 '
0"
#7350
1"
b111 '
1#
#7360
b110 '
0"
#7370
b111 '
1"
#7380
b110 '
0"
#7390
b111 '
1"
#7400
0"
0#
b0 '
0$
#7410
b1 '
1"
#7420
b0 '
0"
#7430
b1 '
1"
#7440
b0 '
0"
#7450
1"
b11 '
1#
#7460
b10 '
0"
#7470
b11 '
1"
#7480
b10 '
0"
#7490
b11 '
1"
#7500
1!
1+
0"
0#
1$
b1100 '
1%
#7510
b1101 '
1"
#7520
b1100 '
0"
#7530
b1101 '
1"
#7540
b1100 '
0"
#7550
1"
b1111 '
1#
#7560
b1110 '
0"
#7570
b1111 '
1"
#7580
b1110 '
0"
#7590
b1111 '
1"
#7600
0"
0#
b1000 '
0$
#7610
b1001 '
1"
#7620
b1000 '
0"
#7630
b1001 '
1"
#7640
b1000 '
0"
#7650
1"
b1011 '
1#
#7660
b1010 '
0"
#7670
b1011 '
1"
#7680
b1010 '
0"
#7690
b1011 '
1"
#7700
0"
0#
b1100 '
1$
#7710
b1101 '
1"
#7720
b1100 '
0"
#7730
b1101 '
1"
#7740
b1100 '
0"
#7750
1"
b1111 '
1#
#7760
b1110 '
0"
#7770
b1111 '
1"
#7780
b1110 '
0"
#7790
b1111 '
1"
#7800
0"
0#
b1000 '
0$
#7810
b1001 '
1"
#7820
b1000 '
0"
#7830
b1001 '
1"
#7840
b1000 '
0"
#7850
1"
b1011 '
1#
#7860
b1010 '
0"
#7870
b1011 '
1"
#7880
b1010 '
0"
#7890
b1011 '
1"
#7900
0"
0#
b1100 '
1$
#7910
b1101 '
1"
#7920
b1100 '
0"
#7930
b1101 '
1"
#7940
b1100 '
0"
#7950
1"
b1111 '
1#
#7960
b1110 '
0"
#7970
b1111 '
1"
#7980
b1110 '
0"
#7990
b1111 '
1"
#8000
0!
0+
0"
0#
0$
b0 '
0%
